airena_player_client/__init__.py
airena_player_client/airena_player_client.py
airena_player_client/env.py
airena_player_client/py.typed
airena_player_client-0.1.1.dist-info/METADATA
airena_player_client-0.1.1.dist-info/WHEEL
airena_player_client-0.1.1.dist-info/RECORD
