Metadata-Version: 2.4
Name: airena-player-client
Version: 0.1.1
Summary: Python client for interacting with the airena game server: queue for games, manage state, and submit moves.
Project-URL: PyPI, https://pypi.org/project/airena-player-client/
Project-URL: GitHub, https://github.com/airena-dev/airena-python-player-client
Author-email: Henry Jones <henryivesjones@gmail.com>
Requires-Python: >=3.12
Requires-Dist: httpx>=0.28.1
Requires-Dist: pydantic-settings>=2.9.1
Requires-Dist: pydantic>=2.11.4
